exotelpy/__init__.py
exotelpy/exceptions.py
exotelpy/exotel.py
exotelpy/helpers.py
exotelpy/validators.py
exotelpy-0.1.1.dist-info/METADATA
exotelpy-0.1.1.dist-info/WHEEL
exotelpy-0.1.1.dist-info/RECORD
